tests/__init__.py
tests/test_cases_parallel.py
tests/st/__init__.py
tests/st/chunk_prefill/__init__.py
tests/st/chunk_prefill/test_native_no_chunk.py
tests/st/chunk_prefill/test_vllm_mf_chunk_prefill.py
tests/st/chunk_prefill/test_vllm_mf_qwen_7b_chunk_prefill_v1.py
tests/st/chunk_prefill/test_vllm_native_chunk_prefill.py
tests/st/distributed/__init__.py
tests/st/distributed/test_mcore_mix_parallel.py
tests/st/distributed/test_shm_broadcast.py
tests/st/kernels/__init__.py
tests/st/kernels/test_attention.py
tests/st/lora/__init__.py
tests/st/lora/test_multilora_inference.py
tests/st/models/__init__.py
tests/st/models/deepseek/__init__.py
tests/st/models/deepseek/offline/__init__.py
tests/st/models/deepseek/offline/test_vllm_deepseek_bf16_part_v1.py
tests/st/models/deepseek/offline/test_vllm_deepseek_part_v1.py
tests/st/models/deepseek/online/__init__.py
tests/st/models/deepseek/online/test_ds_online.py
tests/st/models/glm4/__init__.py
tests/st/models/glm4/test_vllm_glm4_9b_v1.py
tests/st/models/glm4_1v/__init__.py
tests/st/models/glm4_1v/test_vllm_glm4_1v_9b_v1.py
tests/st/models/llama3/__init__.py
tests/st/models/llama3/test_vllm_llama3.py
tests/st/models/minicpm/__init__.py
tests/st/models/minicpm/test_minicpm4_0_5b.py
tests/st/models/qwen2_5/__init__.py
tests/st/models/qwen2_5/test_vllm_mf_qwen_7b_v1.py
tests/st/models/qwen2_5/test_vllm_qwen_7b_v1.py
tests/st/models/qwen2_5_vl/__init__.py
tests/st/models/qwen2_5_vl/similarity.py
tests/st/models/qwen2_5_vl/test_vllm_qwen2_5_vl_7b_v1.py
tests/st/models/qwen3/__init__.py
tests/st/models/qwen3/test_vllm_mf_qwen3_8b.py
tests/st/models/qwen3/test_vllm_qwen3.py
tests/st/models/qwen3_moe/__init__.py
tests/st/models/qwen3_moe/test_vllm_qwen3_moe.py
tests/st/models/qwen3_vl/__init__.py
tests/st/models/qwen3_vl/test_vllm_qwen3_vl_8b_v1.py
tests/st/models/telechat2/__init__.py
tests/st/models/telechat2/test_vllm_mf_telechat2_7b.py
tests/st/prefix_caching/__init__.py
tests/st/prefix_caching/test_vllm_mf_auto_prefix_cache.py
vllm_mindspore-0.5.1.dist-info/licenses/LICENSE
vllm_mindspore-0.5.1.dist-info/METADATA
vllm_mindspore-0.5.1.dist-info/WHEEL
vllm_mindspore-0.5.1.dist-info/entry_points.txt
vllm_mindspore-0.5.1.dist-info/top_level.txt
vllm_mindspore-0.5.1.dist-info/RECORD
