Metadata-Version: 2.4
Name: vllm-mindspore
Version: 0.5.1
Summary: A high-throughput and memory-efficient inference and serving engine for LLMs
Home-page: https://gitee.com/mindspore/vllm-mindspore
Author: MindSpore Team
License: Apache 2.0
Project-URL: Homepage, https://gitee.com/mindspore/vllm-mindspore
Classifier: Programming Language :: Python :: 3.9
Classifier: Programming Language :: Python :: 3.10
Classifier: Programming Language :: Python :: 3.11
Classifier: License :: OSI Approved :: Apache Software License
Classifier: Intended Audience :: Developers
Classifier: Intended Audience :: Information Technology
Classifier: Intended Audience :: Science/Research
Classifier: Topic :: Scientific/Engineering :: Artificial Intelligence
Classifier: Topic :: Scientific/Engineering :: Information Analysis
Requires-Python: >=3.9
License-File: LICENSE
Requires-Dist: ray[default]>=2.48.0
Requires-Dist: transformers==4.57.1
Dynamic: author
Dynamic: classifier
Dynamic: description
Dynamic: description-content-type
Dynamic: home-page
Dynamic: license
Dynamic: license-file
Dynamic: project-url
Dynamic: requires-dist
Dynamic: requires-python
Dynamic: summary
